{
  "instance": "regen_V10_M2_average.txt",
  "route_set_id": "regen_V10_M2_average_rs5",
  "V": 10,
  "M": 2,
  "route_lengths": "2;2",
  "algorithm": "profile-dp",
  "status": "fixed_route_optimal",
  "objective": 1.04316540584,
  "G": 0.41968015539,
  "P": 4.15656833635,
  "runtime_ms": 3.1863,
  "cplex_status": "candidate_mip_optimal_gap0",
  "cplex_objective": 1.04316540584,
  "cplex_G": 0.41968015539,
  "cplex_P": 4.15656833635,
  "cplex_LB": 1.04316540584,
  "cplex_UB": 1.04316540584,
  "cplex_gap": 0,
  "cplex_runtime_ms": 0,
  "cplex_nodes": 0,
  "objective_diff": 3.26094706793e-12,
  "profiles_generated": 293,
  "profiles_after_dominance": 293,
  "profile_bpc_nodes": 10794,
  "profile_bpc_pricing_calls": 2,
  "cache_hits": 0,
  "cache_misses": 0,
  "incremental_speedup": 0,
  "verifier_passed": true,
  "exact_for_fixed_routes": true,
  "result_file": "results/round2_exact_loading\\raw\\regen_V10_M2_average_rs5_profile.json",
  "log_file": "results/round2_exact_loading\\logs\\regen_V10_M2_average_rs5_profile.log",
  "final_inventory": [50000, 1, 11, 5, 28, 1, 27, 23, 10, 23, 17],
  "verification_errors": [],
  "notes": ["Exact mode enumerates all pickup/drop quantities; dominance only merges identical q-vector and final-load profiles keeping the shortest duration."]
}
