{
  "instance": "regen_V20_M2_average.txt",
  "route_set_id": "regen_V20_M2_average_rs7",
  "V": 20,
  "M": 2,
  "route_lengths": "2;1",
  "algorithm": "profile-dp",
  "status": "fixed_route_optimal",
  "objective": 1.57697418349,
  "G": 0.366352701235,
  "P": 8.07080988168,
  "runtime_ms": 1.3331,
  "cplex_status": "candidate_mip_optimal_gap0",
  "cplex_objective": 1.57697418349,
  "cplex_G": 0.366352701235,
  "cplex_P": 8.07080988168,
  "cplex_LB": 1.57697418349,
  "cplex_UB": 1.57697418349,
  "cplex_gap": 0,
  "cplex_runtime_ms": 0,
  "cplex_nodes": 0,
  "objective_diff": 3.41371375612e-12,
  "profiles_generated": 774,
  "profiles_after_dominance": 552,
  "profile_bpc_nodes": 3283,
  "profile_bpc_pricing_calls": 2,
  "cache_hits": 0,
  "cache_misses": 0,
  "incremental_speedup": 0,
  "verifier_passed": true,
  "exact_for_fixed_routes": true,
  "result_file": "results/round2_exact_loading\\raw\\regen_V20_M2_average_rs7_profile.json",
  "log_file": "results/round2_exact_loading\\logs\\regen_V20_M2_average_rs7_profile.log",
  "final_inventory": [50000, 37, 9, 31, 34, 19, 43, 18, 5, 4, 20, 1, 19, 36, 1, 20, 1, 26, 21, 40, 6],
  "verification_errors": [],
  "notes": ["Exact mode enumerates all pickup/drop quantities; dominance only merges identical q-vector and final-load profiles keeping the shortest duration."]
}
